CHANGES.rst
MANIFEST.in
README.rst
setup.cfg
setup.py
src/ps/__init__.py
src/ps.plone.zmi.egg-info/PKG-INFO
src/ps.plone.zmi.egg-info/SOURCES.txt
src/ps.plone.zmi.egg-info/dependency_links.txt
src/ps.plone.zmi.egg-info/entry_points.txt
src/ps.plone.zmi.egg-info/namespace_packages.txt
src/ps.plone.zmi.egg-info/not-zip-safe
src/ps.plone.zmi.egg-info/requires.txt
src/ps.plone.zmi.egg-info/top_level.txt
src/ps/plone/__init__.py
src/ps/plone/zmi/__init__.py
src/ps/plone/zmi/admin.py
src/ps/plone/zmi/configure.zcml
src/ps/plone/zmi/overrides.zcml
src/ps/plone/zmi/patches.py
src/ps/plone/zmi/testing.py
src/ps/plone/zmi/assets/propertyshelf-logo.png
src/ps/plone/zmi/assets/ps-admin-ui.css
src/ps/plone/zmi/templates/propertyshelf-overview.pt
src/ps/plone/zmi/tests/__init__.py
src/ps/plone/zmi/tests/test_views.py