Metadata-Version: 1.1
Name: ps.plone.zmi
Version: 0.3
Summary: ZMI customizations for Plone instances.
Home-page: https://github.com/propertyshelf/ps.plone.zmi
Author: Propertyshelf, Inc.
Author-email: development@propertyshelf.com
License: GPL
Download-URL: http://pypi.python.org/pypi/ps.plone.zmi
Keywords: plone zmi
Platform: UNKNOWN
Classifier: Development Status :: 5 - Production/Stable
Classifier: Environment :: Web Environment
Classifier: Framework :: Plone
Classifier: Framework :: Plone :: 4.2
Classifier: Framework :: Plone :: 4.3
Classifier: Intended Audience :: Developers
Classifier: License :: OSI Approved :: GNU General Public License v2 (GPLv2)
Classifier: Programming Language :: Python
Classifier: Programming Language :: Python :: 2.7
